xplotter/__init__.py
xplotter/formatter.py
xplotter/insights.py
xplotter-0.0.6.dist-info/LICENSE
xplotter-0.0.6.dist-info/METADATA
xplotter-0.0.6.dist-info/WHEEL
xplotter-0.0.6.dist-info/top_level.txt
xplotter-0.0.6.dist-info/RECORD
