Metadata-Version: 2.1
Name: xplotter
Version: 0.0.6
Summary: Explore visual insights from data in an easy and intituitive way with few lines of code.
Home-page: https://github.com/ThiagoPanini/xplotter
Author: Thiago Panini
Author-email: thipanini94@gmail.com
License: MIT
Keywords: Plots,visual analysis,exploratory data analysis,python graphics
Platform: UNKNOWN
Classifier: Programming Language :: Python :: 3
Classifier: Development Status :: 3 - Alpha
Classifier: Environment :: Console
Classifier: Framework :: Jupyter
Classifier: Intended Audience :: Developers
Classifier: Natural Language :: Portuguese (Brazilian)
Classifier: License :: OSI Approved :: MIT License
Classifier: Operating System :: OS Independent
Classifier: Programming Language :: Python :: 3.6
Classifier: Programming Language :: Python :: 3.7
Classifier: Programming Language :: Python :: 3.8
Classifier: Programming Language :: Python :: 3.9
Classifier: Topic :: Software Development :: Libraries :: Python Modules
Requires-Python: >=3.0.0
